lordcommander/__init__.py
lordcommander/commander.py
lordcommander/controllers.py
lordcommander/lcex.py
lordcommander/output.py
lordcommander/utils.py
lordcommander-5.0.1.dist-info/LICENSE
lordcommander-5.0.1.dist-info/METADATA
lordcommander-5.0.1.dist-info/WHEEL
lordcommander-5.0.1.dist-info/entry_points.txt
lordcommander-5.0.1.dist-info/top_level.txt
lordcommander-5.0.1.dist-info/RECORD
