Metadata-Version: 2.1
Name: lordcommander
Version: 5.0.1
Summary: Run shell commands recursively throughout the predefined directories
Home-page: https://github.com/sowrensen/LordCommander
Author: Sowren Sen
Author-email: sowrensen@gmail.com
License: UNKNOWN
Keywords: shell,commands,directory,projects,instances,linux,sever,devops
Platform: UNKNOWN
Classifier: Development Status :: 5 - Production/Stable
Classifier: Environment :: Console
Classifier: Intended Audience :: Developers
Classifier: License :: OSI Approved :: GNU General Public License v3 (GPLv3)
Classifier: Operating System :: Unix
Classifier: Programming Language :: Python :: 3
Classifier: Programming Language :: Python :: 3.7
Classifier: Programming Language :: Python :: 3.8
Classifier: Programming Language :: Python :: 3.9
Classifier: Topic :: Software Development :: Version Control
Classifier: Topic :: System :: Shells
Classifier: Topic :: System :: Installation/Setup
Classifier: Topic :: Terminals
Requires-Python: >=3.7
Requires-Dist: colr (>=0.9)
Requires-Dist: fire (>=0.2)
Requires-Dist: appdirs (>=1.4)
